{
  "type": "FeatureCollection",
  "features": [
    {
      "type": "Feature",
      "geometry": {
        "type": "Point",
        "coordinates": [
          -99.13,
          19.43
        ]
      },
      "properties": {
        "name": "Bacalar",
        "url": "https://www.skylinewebcams.com/en/webcam/mexico/quintana-roo/bacalar/bacalar.html",
        "display_name": "Bacalar",
        "country_code": "MX",
        "environment": "urban",
        "source_family": "skylinewebcams",
        "quality_tier": "premium",
        "scene_type": "urban"
      }
    },
    {
      "type": "Feature",
      "geometry": {
        "type": "Point",
        "coordinates": [
          -109.9167,
          22.8905
        ]
      },
      "properties": {
        "name": "Cabo San Lucas",
        "url": "https://www.skylinewebcams.com/en/webcam/mexico/baja-california-sur/cabo-san-lucas/cabo-san-lucas.html",
        "display_name": "Cabo San Lucas",
        "country_code": "MX",
        "environment": "urban",
        "source_family": "skylinewebcams",
        "quality_tier": "premium",
        "scene_type": "urban"
      }
    },
    {
      "type": "Feature",
      "geometry": {
        "type": "Point",
        "coordinates": [
          -109.9167,
          22.8905
        ]
      },
      "properties": {
        "name": "Cabo San Lucas - Sea Of Cortez",
        "url": "https://www.skylinewebcams.com/en/webcam/mexico/baja-california-sur/cabo-san-lucas/sea-of-cortez.html",
        "display_name": "Cabo San Lucas - Sea Of Cortez",
        "country_code": "MX",
        "environment": "coastal",
        "source_family": "skylinewebcams",
        "quality_tier": "premium",
        "scene_type": "beach"
      }
    },
    {
      "type": "Feature",
      "geometry": {
        "type": "Point",
        "coordinates": [
          -99.13,
          19.43
        ]
      },
      "properties": {
        "name": "Huatulco",
        "url": "https://www.skylinewebcams.com/en/webcam/mexico/oaxaca/huatulco/huatulco.html",
        "display_name": "Huatulco",
        "country_code": "MX",
        "environment": "urban",
        "source_family": "skylinewebcams",
        "quality_tier": "premium",
        "scene_type": "urban"
      }
    },
    {
      "type": "Feature",
      "geometry": {
        "type": "Point",
        "coordinates": [
          -99.13,
          19.43
        ]
      },
      "properties": {
        "name": "Isla Mujeres",
        "url": "https://www.skylinewebcams.com/en/webcam/mexico/quintana-roo/isla-mujeres/isla-mujeres.html",
        "display_name": "Isla Mujeres",
        "country_code": "MX",
        "environment": "urban",
        "source_family": "skylinewebcams",
        "quality_tier": "premium",
        "scene_type": "urban"
      }
    },
    {
      "type": "Feature",
      "geometry": {
        "type": "Point",
        "coordinates": [
          -99.13,
          19.43
        ]
      },
      "properties": {
        "name": "Loreto",
        "url": "https://www.skylinewebcams.com/en/webcam/mexico/baja-california-sur/loreto/loreto.html",
        "display_name": "Loreto",
        "country_code": "MX",
        "environment": "urban",
        "source_family": "skylinewebcams",
        "quality_tier": "premium",
        "scene_type": "urban"
      }
    },
    {
      "type": "Feature",
      "geometry": {
        "type": "Point",
        "coordinates": [
          -98.25,
          18.92
        ]
      },
      "properties": {
        "name": "Mexico - Cabo San Lucas",
        "url": "https://hd-auth.skylinewebcams.com/live.m3u8?a=f8fuim9btgohm6m6esci6492k7",
        "display_name": "Mexico",
        "country_code": "MX",
        "environment": "urban",
        "source_family": "skylinewebcams",
        "quality_tier": "premium",
        "scene_type": "urban_panorama"
      }
    },
    {
      "type": "Feature",
      "geometry": {
        "type": "Point",
        "coordinates": [
          -99.1332,
          19.4326
        ]
      },
      "properties": {
        "name": "Mexico City",
        "url": "https://www.skylinewebcams.com/en/webcam/mexico/federal-district/mexico-city/mexico-city.html",
        "display_name": "Mexico City",
        "country_code": "MX",
        "environment": "urban",
        "source_family": "skylinewebcams",
        "quality_tier": "premium",
        "scene_type": "urban"
      }
    },
    {
      "type": "Feature",
      "geometry": {
        "type": "Point",
        "coordinates": [
          -99.1332,
          19.4326
        ]
      },
      "properties": {
        "name": "Mexico City - Alcaldia",
        "url": "https://www.skylinewebcams.com/en/webcam/mexico/federal-district/mexico-city/alcaldia.html",
        "display_name": "Mexico City - Alcaldia",
        "country_code": "MX",
        "environment": "urban",
        "source_family": "skylinewebcams",
        "quality_tier": "premium",
        "scene_type": "urban"
      }
    },
    {
      "type": "Feature",
      "geometry": {
        "type": "Point",
        "coordinates": [
          -99.1332,
          19.4326
        ]
      },
      "properties": {
        "name": "Mexico City - Monumento A La Revolucion",
        "url": "https://www.skylinewebcams.com/en/webcam/mexico/federal-district/mexico-city/monumento-a-la-revolucion.html",
        "display_name": "Mexico City - Monumento A La Revolucion",
        "country_code": "MX",
        "environment": "urban",
        "source_family": "skylinewebcams",
        "quality_tier": "premium",
        "scene_type": "urban"
      }
    },
    {
      "type": "Feature",
      "geometry": {
        "type": "Point",
        "coordinates": [
          -99.1332,
          19.4326
        ]
      },
      "properties": {
        "name": "Mexico City - Panorama",
        "url": "https://www.skylinewebcams.com/en/webcam/mexico/federal-district/mexico-city/panorama.html",
        "display_name": "Mexico City - Panorama",
        "country_code": "MX",
        "environment": "urban",
        "source_family": "skylinewebcams",
        "quality_tier": "premium",
        "scene_type": "urban"
      }
    },
    {
      "type": "Feature",
      "geometry": {
        "type": "Point",
        "coordinates": [
          -99.1332,
          19.4326
        ]
      },
      "properties": {
        "name": "Mexico City - Plaza Garibaldi",
        "url": "https://www.skylinewebcams.com/en/webcam/mexico/federal-district/mexico-city/plaza-garibaldi.html",
        "display_name": "Mexico City - Plaza Garibaldi",
        "country_code": "MX",
        "environment": "urban",
        "source_family": "skylinewebcams",
        "quality_tier": "premium",
        "scene_type": "urban"
      }
    },
    {
      "type": "Feature",
      "geometry": {
        "type": "Point",
        "coordinates": [
          -99.1332,
          19.4326
        ]
      },
      "properties": {
        "name": "Mexico City - Zocalo",
        "url": "https://www.skylinewebcams.com/en/webcam/mexico/federal-district/mexico-city/zocalo.html",
        "display_name": "Mexico City - Zocalo",
        "country_code": "MX",
        "environment": "urban",
        "source_family": "skylinewebcams",
        "quality_tier": "premium",
        "scene_type": "urban"
      }
    },
    {
      "type": "Feature",
      "geometry": {
        "type": "Point",
        "coordinates": [
          -99.13,
          19.43
        ]
      },
      "properties": {
        "name": "Pachuca - Plaza",
        "url": "https://www.skylinewebcams.com/en/webcam/mexico/hidalgo/pachuca/plaza.html",
        "display_name": "Pachuca - Plaza",
        "country_code": "MX",
        "environment": "urban",
        "source_family": "skylinewebcams",
        "quality_tier": "premium",
        "scene_type": "urban"
      }
    },
    {
      "type": "Feature",
      "geometry": {
        "type": "Point",
        "coordinates": [
          -99.13,
          19.43
        ]
      },
      "properties": {
        "name": "Puebla",
        "url": "https://www.skylinewebcams.com/en/webcam/mexico/puebla/puebla/puebla.html",
        "display_name": "Puebla",
        "country_code": "MX",
        "environment": "urban",
        "source_family": "skylinewebcams",
        "quality_tier": "premium",
        "scene_type": "urban"
      }
    },
    {
      "type": "Feature",
      "geometry": {
        "type": "Point",
        "coordinates": [
          -100.01,
          18.6
        ]
      },
      "properties": {
        "name": "Puerto Escondido - Mexico",
        "url": "https://hd-auth.skylinewebcams.com/live.m3u8?a=as5bl4hj1bhs8rfrpd0krdd0f0",
        "display_name": "Puerto Escondido",
        "country_code": "MX",
        "environment": "urban",
        "source_family": "skylinewebcams",
        "quality_tier": "premium",
        "scene_type": "urban_panorama"
      }
    },
    {
      "type": "Feature",
      "geometry": {
        "type": "Point",
        "coordinates": [
          -99.13,
          19.43
        ]
      },
      "properties": {
        "name": "Puerto Morelos",
        "url": "https://www.skylinewebcams.com/en/webcam/mexico/quintana-roo/puerto-morelos/puerto-morelos.html",
        "display_name": "Puerto Morelos",
        "country_code": "MX",
        "environment": "urban",
        "source_family": "skylinewebcams",
        "quality_tier": "premium",
        "scene_type": "urban"
      }
    },
    {
      "type": "Feature",
      "geometry": {
        "type": "Point",
        "coordinates": [
          -105.2253,
          20.6534
        ]
      },
      "properties": {
        "name": "Puerto Vallarta",
        "url": "https://www.skylinewebcams.com/en/webcam/mexico/jalisco/puerto-vallarta/puerto-vallarta.html",
        "display_name": "Puerto Vallarta",
        "country_code": "MX",
        "environment": "urban",
        "source_family": "skylinewebcams",
        "quality_tier": "premium",
        "scene_type": "urban"
      }
    },
    {
      "type": "Feature",
      "geometry": {
        "type": "Point",
        "coordinates": [
          -105.2253,
          20.6534
        ]
      },
      "properties": {
        "name": "Puerto Vallarta - Playa",
        "url": "https://www.skylinewebcams.com/en/webcam/mexico/jalisco/puerto-vallarta/playa.html",
        "display_name": "Puerto Vallarta - Playa",
        "country_code": "MX",
        "environment": "coastal",
        "source_family": "skylinewebcams",
        "quality_tier": "premium",
        "scene_type": "beach"
      }
    },
    {
      "type": "Feature",
      "geometry": {
        "type": "Point",
        "coordinates": [
          -99.13,
          19.43
        ]
      },
      "properties": {
        "name": "San Carlos",
        "url": "https://www.skylinewebcams.com/en/webcam/mexico/sonora/san-carlos/san-carlos.html",
        "display_name": "San Carlos",
        "country_code": "MX",
        "environment": "urban",
        "source_family": "skylinewebcams",
        "quality_tier": "premium",
        "scene_type": "urban"
      }
    },
    {
      "type": "Feature",
      "geometry": {
        "type": "Point",
        "coordinates": [
          -99.13,
          19.43
        ]
      },
      "properties": {
        "name": "San Joaquin",
        "url": "https://www.skylinewebcams.com/en/webcam/mexico/queretaro/san-joaquin/san-joaquin.html",
        "display_name": "San Joaquin",
        "country_code": "MX",
        "environment": "urban",
        "source_family": "skylinewebcams",
        "quality_tier": "premium",
        "scene_type": "urban"
      }
    },
    {
      "type": "Feature",
      "geometry": {
        "type": "Point",
        "coordinates": [
          -99.13,
          19.43
        ]
      },
      "properties": {
        "name": "San Pedro Benito Juarez - Popocatepetl",
        "url": "https://www.skylinewebcams.com/en/webcam/mexico/puebla/san-pedro-benito-juarez/popocatepetl.html",
        "display_name": "San Pedro Benito Juarez - Popocatepetl",
        "country_code": "MX",
        "environment": "urban",
        "source_family": "skylinewebcams",
        "quality_tier": "premium",
        "scene_type": "urban"
      }
    },
    {
      "type": "Feature",
      "geometry": {
        "type": "Point",
        "coordinates": [
          -99.13,
          19.43
        ]
      },
      "properties": {
        "name": "San Pedro Mixtepec - Puerto Escondido",
        "url": "https://www.skylinewebcams.com/en/webcam/mexico/oaxaca/san-pedro-mixtepec/puerto-escondido.html",
        "display_name": "San Pedro Mixtepec - Puerto Escondido",
        "country_code": "MX",
        "environment": "urban",
        "source_family": "skylinewebcams",
        "quality_tier": "premium",
        "scene_type": "urban"
      }
    },
    {
      "type": "Feature",
      "geometry": {
        "type": "Point",
        "coordinates": [
          -99.13,
          19.43
        ]
      },
      "properties": {
        "name": "Solidaridad - Cancun Quintana Roo",
        "url": "https://www.skylinewebcams.com/en/webcam/mexico/quintana-roo/solidaridad/cancun-quintana-roo.html",
        "display_name": "Solidaridad - Cancun Quintana Roo",
        "country_code": "MX",
        "environment": "urban",
        "source_family": "skylinewebcams",
        "quality_tier": "premium",
        "scene_type": "urban"
      }
    },
    {
      "type": "Feature",
      "geometry": {
        "type": "Point",
        "coordinates": [
          -99.13,
          19.43
        ]
      },
      "properties": {
        "name": "Solidaridad - Cancun Swimming Pools",
        "url": "https://www.skylinewebcams.com/en/webcam/mexico/quintana-roo/solidaridad/cancun-swimming-pools.html",
        "display_name": "Solidaridad - Cancun Swimming Pools",
        "country_code": "MX",
        "environment": "urban",
        "source_family": "skylinewebcams",
        "quality_tier": "premium",
        "scene_type": "urban"
      }
    },
    {
      "type": "Feature",
      "geometry": {
        "type": "Point",
        "coordinates": [
          -99.13,
          19.43
        ]
      },
      "properties": {
        "name": "Solidaridad - Cancun The Royal Sands",
        "url": "https://www.skylinewebcams.com/en/webcam/mexico/quintana-roo/solidaridad/cancun-the-royal-sands.html",
        "display_name": "Solidaridad - Cancun The Royal Sands",
        "country_code": "MX",
        "environment": "urban",
        "source_family": "skylinewebcams",
        "quality_tier": "premium",
        "scene_type": "urban"
      }
    },
    {
      "type": "Feature",
      "geometry": {
        "type": "Point",
        "coordinates": [
          -99.13,
          19.43
        ]
      },
      "properties": {
        "name": "Solidaridad - El Parque De Xcaret",
        "url": "https://www.skylinewebcams.com/en/webcam/mexico/quintana-roo/solidaridad/el-parque-de-xcaret.html",
        "display_name": "Solidaridad - El Parque De Xcaret",
        "country_code": "MX",
        "environment": "urban",
        "source_family": "skylinewebcams",
        "quality_tier": "premium",
        "scene_type": "urban"
      }
    },
    {
      "type": "Feature",
      "geometry": {
        "type": "Point",
        "coordinates": [
          -99.13,
          19.43
        ]
      },
      "properties": {
        "name": "Solidaridad - Panorama De Playa Del Carmen",
        "url": "https://www.skylinewebcams.com/en/webcam/mexico/quintana-roo/solidaridad/panorama-de-playa-del-carmen.html",
        "display_name": "Solidaridad - Panorama De Playa Del Carmen",
        "country_code": "MX",
        "environment": "coastal",
        "source_family": "skylinewebcams",
        "quality_tier": "premium",
        "scene_type": "beach"
      }
    },
    {
      "type": "Feature",
      "geometry": {
        "type": "Point",
        "coordinates": [
          -99.13,
          19.43
        ]
      },
      "properties": {
        "name": "Solidaridad - Panorama Of Cancun",
        "url": "https://www.skylinewebcams.com/en/webcam/mexico/quintana-roo/solidaridad/panorama-of-cancun.html",
        "display_name": "Solidaridad - Panorama Of Cancun",
        "country_code": "MX",
        "environment": "urban",
        "source_family": "skylinewebcams",
        "quality_tier": "premium",
        "scene_type": "urban"
      }
    },
    {
      "type": "Feature",
      "geometry": {
        "type": "Point",
        "coordinates": [
          -99.13,
          19.43
        ]
      },
      "properties": {
        "name": "Teotihuacan",
        "url": "https://www.skylinewebcams.com/en/webcam/mexico/federal-district/teotihuacan/teotihuacan.html",
        "display_name": "Teotihuacan",
        "country_code": "MX",
        "environment": "urban",
        "source_family": "skylinewebcams",
        "quality_tier": "premium",
        "scene_type": "urban"
      }
    },
    {
      "type": "Feature",
      "geometry": {
        "type": "Point",
        "coordinates": [
          -87.4654,
          20.2114
        ]
      },
      "properties": {
        "name": "Tulum - Playa",
        "url": "https://www.skylinewebcams.com/en/webcam/mexico/quintana-roo/tulum/playa.html",
        "display_name": "Tulum - Playa",
        "country_code": "MX",
        "environment": "coastal",
        "source_family": "skylinewebcams",
        "quality_tier": "premium",
        "scene_type": "beach"
      }
    },
    {
      "type": "Feature",
      "geometry": {
        "type": "Point",
        "coordinates": [
          -99.13,
          19.43
        ]
      },
      "properties": {
        "name": "Vallecillo",
        "url": "https://www.skylinewebcams.com/en/webcam/mexico/nuevo-leon/vallecillo/vallecillo.html",
        "display_name": "Vallecillo",
        "country_code": "MX",
        "environment": "urban",
        "source_family": "skylinewebcams",
        "quality_tier": "premium",
        "scene_type": "urban"
      }
    },
    {
      "type": "Feature",
      "geometry": {
        "type": "Point",
        "coordinates": [
          -99.01,
          19.72
        ]
      },
      "properties": {
        "name": "Vallecillo - Mexico",
        "url": "https://hd-auth.skylinewebcams.com/live.m3u8?a=jj24jkf20oahu9h2vrk5f29gc2",
        "display_name": "Vallecillo",
        "country_code": "MX",
        "environment": "urban",
        "source_family": "skylinewebcams",
        "quality_tier": "premium",
        "scene_type": "urban_panorama"
      }
    },
    {
      "type": "Feature",
      "geometry": {
        "type": "Point",
        "coordinates": [
          -0.8773,
          41.6561
        ]
      },
      "properties": {
        "name": "Zaragoza - Border",
        "url": "https://www.skylinewebcams.com/en/webcam/mexico/chihuahua/zaragoza/border.html",
        "display_name": "Zaragoza - Border",
        "country_code": "MX",
        "environment": "urban",
        "source_family": "skylinewebcams",
        "quality_tier": "premium",
        "scene_type": "urban"
      }
    },
    {
      "type": "Feature",
      "geometry": {
        "type": "Point",
        "coordinates": [
          -99.13,
          19.43
        ]
      },
      "properties": {
        "name": "Zihuatanejo - Ixtapa",
        "url": "https://www.skylinewebcams.com/en/webcam/mexico/guerrero/zihuatanejo/ixtapa.html",
        "display_name": "Zihuatanejo - Ixtapa",
        "country_code": "MX",
        "environment": "urban",
        "source_family": "skylinewebcams",
        "quality_tier": "premium",
        "scene_type": "urban"
      }
    },
    {
      "type": "Feature",
      "geometry": {
        "type": "Point",
        "coordinates": [
          -99.13,
          19.43
        ]
      },
      "properties": {
        "name": "Zihuatanejo - Playa La Madera",
        "url": "https://www.skylinewebcams.com/en/webcam/mexico/guerrero/zihuatanejo/playa-la-madera.html",
        "display_name": "Zihuatanejo - Playa La Madera",
        "country_code": "MX",
        "environment": "coastal",
        "source_family": "skylinewebcams",
        "quality_tier": "premium",
        "scene_type": "beach"
      }
    }
  ]
}